<?xml version="1.0" encoding="utf-8"?>
<!--
Polish translation of DuckDuckGo for Android
Autors: m4sk1n <m4sk1n at vivaldi dot net> -->
<resources>
	<string name="WarnSSLDetail">Certyfikat SSL serwera nie jest zapisany jako zaufany.\nNadal możesz  kontynuować lub anulować zadanie.</string>
	<string name="WarnSSLTitle">Ostrzeżenie: Certyfikat SSL</string>
	<string name="sha1_fingerprint">Odcisk palca SHA-1:</string>
	<string name="sha256_fingerprint">Odcisk palca SHA-256:</string>
	<string name="fingerprints">Odciski palców:</string>
	<string name="serial_number">Numer seryjny:</string>
	<string name="expires_on">Wygasa:</string>
	<string name="issued_on">Zgłoszono na:</string>
	<string name="validity_period">Ważność:</string>
	<string name="issued_by">Zgłoszono przez:</string>
	<string name="org_unit">Jednostka organizacyjna:</string>
	<string name="org_name">Organizacja:</string>
	<string name="common_name">Ogólna nazwa:</string>
	<string name="issued_to">Zgłoszono do:</string>
	<string name="ssl_certificate_is_valid">Ten certyfikat jest prawidłowy.</string>
	<string name="ssl_certificate">Certyfikat bezpieczeństwa</string>
	<string name="remove">Usuń</string>
	<string name="action_close">Zamknij</string>
	<string name="action_forward">Dalej</string>
	<string name="action_back">Wstecz</string>
	<string name="action_view_external">Pokaż w przeglądarce</string>
	<string name="action_share">Udostępnij</string>
	<string name="action_remove_favorite">Usuń z ulubionych</string>
	<string name="action_add_favorite">Dodaj do ulubionych</string>
	<string name="action_reload">Odśwież stronę</string>
	<string name="action_help_feedback">Pomoc i opinie</string>
	<string name="action_settings">\@string/settings</string>
	<string name="action_favorites">\@string/favorites</string>
	<string name="action_recents">\@string/recents</string>
	<string name="action_stories">\@string/stories</string>
	<string name="options">Opcje</string>
	<string name="change_sources">Źródła</string>
	<string name="rate">Oceń aplikację</string>
	<string name="leave_feedback">Zostaw opinię</string>
	<string name="feedback">Opinie</string>
	<string name="android_help_center">Centrum pomocy dla Androida</string>
	<string name="help">Pomoc</string>
	<string name="select_application">Wybierz aplikację</string>
	<string name="version">Wersja</string>
	<string name="about_text">Wyszukiwarka, która cię\nnie śledzi.</string>
	<string name="about">O programie</string>
	<string name="disabled_recents_text">Możesz wyłączyć ostatnie w ustawieniach</string>
	<string name="disabled_recents_title">Ostatnie wyłączone</string>
	<string name="empty_recents_text">Kiedy rozpoczniesz wyszukiwanie\nlub przeglądanie opowieści,\ntwoja aktywność pojawi się tutaj.</string>
	<string name="empty_recents_title">Brak ostatnich</string>
	<string name="recent_searches_narrow">Wyszukiwania</string>
	<string name="recent_searches">Ostatnie wyszukiwania</string>
	<string name="recent_stories_narrow">\@string/stories</string>
	<string name="recent_stories">Ostatnie opowieści</string>
	<string name="recents">Ostatnie</string>
	<string name="empty_favorites_text">Dodaj wyszukiwania\ni opowieści do ulubionych,\naby były tu wyświetlane.</string>
	<string name="empty_favorites_title">Brak ulubionych</string>
	<string name="favorite_search_narrow">Wyszukiwania</string>
	<string name="favorite_search">Ulubione wyszukiwania</string>
	<string name="favorite_stories_narrow">\@string/stories</string>
	<string name="favorite_stories">Ulubione opowieści</string>
	<string name="favorites">Ulubione</string>
	<string name="settings">Ustawienia</string>
	<string name="help_feedback">Pomoc i opinie</string>
	<string name="stories">Opowieści</string>
	<string name="WorldTraveler">Światowy Podróżnik (żaden)</string>
	<string name="NewSourcesNoThx">Później</string>
	<string name="NewSourcesOk">Pokaż</string>
	<string name="NewSources">Dodaliśmy kilka ciekawych źródeł opowieści!</string>
	<string name="LeftRecentStories">Ostatnie opowieści</string>
	<string name="LeftRecentSearches">Ostatnie wyszukiwania</string>
	<string name="BangButtonExplanation">Wyszukiwanie na innych stronach jest proste korzystając z komend !bang.</string>
	<string name="GetStarted">Rozpocznij</string>
	<string name="WelcomeDescription">\n        Szukaj anonimowo.\nZnajduj natychmiastowo.\nPozostań zainformowany.</string>
	<string name="WelcomeTitle">DuckDuckGo - wyszukiwania i opowieści</string>
	<string name="WelcomeHeader">Wprowadzenie</string>
	<string name="ToastDeleteUrlInHistory">Adres został usunięty z twojej historii.</string>
	<string name="ToastDeleteStoryInHistory">Opowieść została usunięta z twojej historii.</string>
	<string name="ToastSaveSearch">Twoje wyszukiwanie zostało zapisane.</string>
	<string name="ToastSaveStory">Ta opowieść została zapisana.</string>
	<string name="ToastUnSaveSearch">Wyszukiwanie zostało usunięte z twoich wyszukiwań</string>
	<string name="ToastUnSaveStory">Opowieść została usunięta z twoich zapisanych opowieści.</string>
	<string name="PageOptionsTitle">Opcje strony</string>
	<string name="SearchOptionsTitle">Opcje wyszukiwania</string>
	<string name="StoryOptionsTitle">Opcje opowieści</string>
	<string name="SavedStories">Zapisane opowieści</string>
	<string name="SavedSearches">Zapisane wyszukiwania</string>
	<string name="ReadabilityOff">Usprawnienie czytelności wyłączone</string>
	<string name="ReadabilityOn">Usprawnienie czytelności włączone</string>
	<string name="SelectAppToSend">Wyślij aplikację do wysłania</string>
	<string name="OnlyOnPhone">Tylko w telefonie</string>
	<string name="NoChange">Bez zmian</string>
	<string name="Cancel">Anuluj</string>
	<string name="Apply">Zastosuj</string>
	<string name="ErrorFeedDetail">Zgloszenie kanału nie udało się, prawdopodobnie ze względu na problem z połączeniem.\nNadal możesz przeglądać elementy z pamięci podręcznej, lub spróbować ponownie.</string>
	<string name="ErrorFeedTitle">Błąd: zgłoszenie kanału</string>
	<string name="Retry">Ponów</string>
	<string name="Continue">Kontynuuj</string>
	<string name="InformHistory">jest wyłączone. Możesz włączyć w</string>
	<string name="WaterCoolerSources">Opowieści</string>
	<string name="SummaryWaterCooler">\n        Te źródła utworzą strumień interesujących opowieści, których nie znajdziesz w zwykłych aplikacji z wiadomościami.\n        Wszystkie źródła są oparte na kanałach takich jak "najbardziej udostępniane" czy "najczęściej oceniane"\n        Sprawdź tą funkcję, kiedy znajdziesz wolne pięć minut.\n        Informacja: możesz usunąć Opowieści z ekranu głównego używając ustawienia "Ekran główny".\n    </string>
	<string name="Loading">Ładowanie...</string>
	<string name="SuggestSourceToast">Do zaimplementowania</string>
	<string name="DefaultsSetToast">Przywrócono źródła do ustawień domyślnych.</string>
	<string name="InfoReadStoriesFromCache">Połączenie nie powiodło się! Opowieści zostały usunięte z pamięci podręcznej...</string>
	<string name="ToastDownloadManagerUnavailable">Nie udało się pobrać pliku</string>
	<string name="ToastSchemeNotSupported">Nie udało się pobrać pliku</string>
	<string name="ErrorDownloadOpenFail">Pobrany plik nie może zostać otwarty!</string>
	<string name="ErrorDownloadFailed">Pobieranie nie powiodło się!</string>
	<string name="ErrorActivityNotFound">Nie znaleziono podobnej aktywności!</string>
	<string name="ErrorAppNotFound">Nie znaleziono aplikacji</string>
	<string name="crash_dialog_ok_toast">Dziękujemy za pomoc!</string>
	<string name="crash_dialog_comment_prompt">Twój komentarz:</string>
	<string name="crash_dialog_text">Wystąpił nieoczekiwany błąd.\n        Prosimy o pomoc w naprawieniu problemu klikając \'OK\', aby przesłać raport o błędzie. \n        Jedyne dane, które otrzymamy to: APP_VERSION_CODE, APP_VERSION_NAME, ANDROID_VERSION, STACK_TRACE,\n        AVAILABLE_MEM_SIZE, ReportField.USER_COMMENT i LOGCAT.</string>
	<string name="crash_notif_text">Naciśnij tutaj aby pomóc w naprawieniu tego błędu.</string>
	<string name="crash_notif_title">Raport o błędzie DuckDuckGo</string>
	<string name="crash_notif_ticker_text">Wystąpił nieoczekiwany błąd, prosimy o wysłanie raportu...</string>
	<string name="crash_toast_text">Aplikacja została zatrzymana! Informacje związane z tym zostaną zebrane i zgłoszone za pozwoleniem.</string>
	<string name="ChangingFontSize">Zmiana rozmiaru czcionki...</string>
	<string name="ConfirmExternalBrowser">Proszę potwierdzić</string>
	<string name="OpenInExternalBrowser">Otwórz w zewnętrznej przeglądarce</string>
	<string name="MoreMenuTitle">Opcje strony</string>
	<string name="SavedResultsEmptySubTitle">Możesz zapisać swoje wyniki wyszukiwania w menu akcji paska wyszukiwania.</string>
	<string name="SavedResultsEmptyTitle">Nie zapisałeś żadnych wyników</string>
	<string name="SavedFeedEmptySubTitle">Możesz zapisać opowieści z menu akcji paska wyszukiwania.</string>
	<string name="SavedFeedEmptyTitle">Nie masz żadnych zapisanych opowieści</string>
	<string name="FeedbackSubject">DuckDuckGo Android v2</string>
	<string name="FeedbackTo">Opinie o DuckDuckGo  &lt;help@duckduckgo.com></string>
	<string name="SuggestedSources">Polecamy dodać te źródła:</string>
	<string name="SuggestSource">Zaproponuj źródło</string>
	<string name="Defaults">Przywróć do domyślnych</string>
	<string name="Default">Domyślne</string>
	<string name="ConfirmClearCacheAndCookies">Pamięć podręczna zostanie usunięta. Czy jesteś tego pewien?</string>
	<string name="ConfirmClearCookies">Wszystkie pliki cookies zostaną usunięte. Czy jesteś tego pewien?</string>
	<string name="ConfirmClearHistory">Cała historia wyszukiwania zostanie usunięta. Czy jesteś tego pewien?</string>
	<string name="Confirm">Potwierdź</string>
	<string name="LeftRecentQueries">Ostatnie żądania</string>
	<string name="LeftRecent">Ostatnie</string>
	<string name="LeftSettings">Ustawienia</string>
	<string name="LeftSaved">Zapisane</string>
	<string name="LeftStories">Opowieści</string>
	<string name="Delete">Usuń</string>
	<string name="Refresh">Odśwież</string>
	<string name="Share">Udostępnij</string>
	<string name="Unsave">Usuń z zapisanych</string>
	<string name="Save">Zapisz</string>
	<string name="No">Nie</string>
	<string name="Yes">Tak</string>
	<string name="TwitterShareFormat">%1$s przes @duckduckgo na Androida</string>
	<string name="RegularShareFormat">%1$s przez DuckDuckGo na Androida</string>
	<string name="SharePage">Udostępnij stronę</string>
	<string name="ShareSearch">Udostępnij wyszukiwanie</string>
	<string name="ShareStory">Udostępnij opowieść</string>
	<string name="OrbotCheckSite">https://check.torproject.org</string>
	<string name="OrbotStatusOkMessage">Wygląda na to, że Orbot działa poprawnie!</string>
	<string name="OrbotStatusOkTitle">Status Orbot</string>
	<string name="PrefCheckOrbotStatus">Sprawdź status Orbot</string>
	<string name="PrefEnableTor">Włącz Tor</string>
	<string name="PrefGroupTor">Tor</string>
	<string name="PrefReadableSummary">Włączony, kiedy dostępny</string>
	<string name="PrefReadable">Czytelność</string>
	<string name="PrefAutoUpdate">Automatyczne odświeżanie kanałów</string>
	<string name="PrefTurnOffAutocomplete">Wyłączone</string>
	<string name="PrefSearchResults">Wyniki wyszukiwania</string>
	<string name="PrefAutocomplete">Autouzupełnianie</string>
	<string name="PrefWaterCooler">Opowieści</string>
	<string name="PrefEnableJavascript">Włącz JavaScript</string>
	<string name="PrefAcraEnabled">Automatyczne raportowanie błędów włączone</string>
	<string name="PrefAcraDisabled">Automatyczne raportowanie błędów wyłączone</string>
	<string name="PrefEnableAcra">Automatyczne raportowanie błędów</string>
	<string name="PrefMainFontSize">Rozmiar czcionki</string>
	<string name="PrefAppSearch">Wlicz aplikacje</string>
	<string name="PrefRate">Oceń aplikację</string>
	<string name="PrefAbout">O programie</string>
	<string name="PrefSendFeedback">Pozostaw opinię</string>
	<string name="PrefClearCacheCookiesMonthly">Co miesiąc</string>
	<string name="PrefClearCacheCookiesWeekly">Co tydzień</string>
	<string name="PrefClearCacheCookiesEveryLaunch">Przy każdym uruchomieniu</string>
	<string name="PrefExternalBrowserAlways">Zawsze</string>
	<string name="PrefExternalBrowserExceptSearches">Poza wynikami wyszukiwania</string>
	<string name="PrefNever">Nigdy</string>
	<string name="PrefExternalBrowser">Używaj zewnętrznej przeglądarki</string>
	<string name="PrefDirectQuery">Szukaj po naciśnięciu</string>
	<string name="PrefRegion">Region</string>
	<string name="PrefResetSources">Resetuj źródła</string>
	<string name="PrefSources">Źródła</string>
	<string name="PrefClearCacheAndCookies">Wyczyść pliki cookies i pamięć podręczną</string>
	<string name="PrefClearBrowserCache">Wyczyść pamięć podręczną</string>
	<string name="PrefClearCookies">Wyczyszczono pliki cookies</string>
	<string name="PrefRecordCookies">Zapisz pliki cookies</string>
	<string name="PrefClearHistory">Wyczyść ostatnie</string>
	<string name="PrefRecordHistory">Zapisz ostatnie</string>
	<string name="PrefRecentSearch">\@string/recents</string>
	<string name="PrefDuckMode">Szukaj</string>
	<string name="PrefSavedItems">\@string/favorites</string>
	<string name="PrefWaterCoolerStories">Opowieści</string>
	<string name="PrefStories">Opowieści</string>
	<string name="PrefStartScreen">Strona główna</string>
	<string name="PrefThemeDark">Ciemny</string>
	<string name="PrefThemeLight">Jasny</string>
	<string name="PrefTheme">Motyw</string>
	<string name="PrefGroupFeedback">Opinie</string>
	<string name="PrefGroupPrivacy">Prywatność</string>
	<string name="PrefGroupAppFlow">Aplikacja</string>
	<string name="PrefGroupOther">Inne</string>
	<string name="PrefGroupSearch">Szukaj</string>
	<string name="PrefGroupStories">Opowieści</string>
	<string name="PrefGroupGeneral">Ogólne</string>
	<string name="search_hint">Szukaj...</string>
	<string name="HomeButtonContentDescription">Strona główna</string>
	<string name="SettingsButtonContentDescription">Ustawienia</string>
	<string name="SearchStringBig">Szukaj w DuckDuckGo lub wprowadź adres URL</string>
	<string name="SearchStringSmall">Szukaj w DDG lub wpisz adres URL</string>
	<string name="AppName">DuckDuckGo</string>
</resources>
